rldb/__init__.py
rldb/find.py
rldb/normalization.py
rldb/db/__init__.py
rldb/db/paper__a3c/__init__.py
rldb/db/paper__a3c/algo__a3c_ff/__init__.py
rldb/db/paper__a3c/algo__a3c_ff/entries.py
rldb/db/paper__a3c/algo__a3c_ff_1_day/__init__.py
rldb/db/paper__a3c/algo__a3c_ff_1_day/entries.py
rldb/db/paper__a3c/algo__a3c_lstm/__init__.py
rldb/db/paper__a3c/algo__a3c_lstm/entries.py
rldb/db/paper__acktr/__init__.py
rldb/db/paper__acktr/algo__a2c/__init__.py
rldb/db/paper__acktr/algo__a2c/entries.py
rldb/db/paper__acktr/algo__acktr/__init__.py
rldb/db/paper__acktr/algo__acktr/entries.py
rldb/db/paper__acktr/algo__trpo/__init__.py
rldb/db/paper__acktr/algo__trpo/entries.py
rldb/db/paper__c51/__init__.py
rldb/db/paper__c51/algo__c51/__init__.py
rldb/db/paper__c51/algo__c51/entries.py
rldb/db/paper__c51/algo__ddqn/__init__.py
rldb/db/paper__c51/algo__ddqn/entries.py
rldb/db/paper__c51/algo__dqn/__init__.py
rldb/db/paper__c51/algo__dqn/entries.py
rldb/db/paper__ddqn/__init__.py
rldb/db/paper__ddqn/algo__ddqn/__init__.py
rldb/db/paper__ddqn/algo__ddqn/entries.py
rldb/db/paper__ddqn/algo__ddqn_tuned/__init__.py
rldb/db/paper__ddqn/algo__ddqn_tuned/entries.py
rldb/db/paper__ddqn/algo__human/__init__.py
rldb/db/paper__ddqn/algo__human/entries.py
rldb/db/paper__ddqn/algo__random/__init__.py
rldb/db/paper__ddqn/algo__random/entries.py
rldb/db/paper__dqn/__init__.py
rldb/db/paper__dqn/algo__bll/__init__.py
rldb/db/paper__dqn/algo__bll/entries.py
rldb/db/paper__dqn/algo__contingency/__init__.py
rldb/db/paper__dqn/algo__contingency/entries.py
rldb/db/paper__dqn/algo__dqn/__init__.py
rldb/db/paper__dqn/algo__dqn/entries.py
rldb/db/paper__dqn/algo__human/__init__.py
rldb/db/paper__dqn/algo__human/entries.py
rldb/db/paper__dqn/algo__random/__init__.py
rldb/db/paper__dqn/algo__random/entries.py
rldb/db/paper__dqn2013/__init__.py
rldb/db/paper__dqn2013/algo__contingency/__init__.py
rldb/db/paper__dqn2013/algo__contingency/entries.py
rldb-0.0.0.dist-info/METADATA
rldb-0.0.0.dist-info/RECORD
rldb-0.0.0.dist-info/WHEEL
rldb-0.0.0.dist-info/top_level.txt
