Metadata-Version: 2.1
Name: rldb
Version: 0.0.0
Summary: Performances of Reinforcement Learning Agents
Home-page: https://github.com/seungjaeryanlee/rldb
Author: Seungjae (Ryan) Lee
Author-email: seungjaeryanlee@gmail.com
License: UNKNOWN
Platform: UNKNOWN
Classifier: Programming Language :: Python :: 3
Classifier: License :: OSI Approved :: MIT License
Classifier: Operating System :: OS Independent
